secure_authenticator/__init__.py
secure_authenticator/secure_authenticator.py
secure_authenticator-1.6.dist-info/METADATA
secure_authenticator-1.6.dist-info/WHEEL
secure_authenticator-1.6.dist-info/top_level.txt
secure_authenticator-1.6.dist-info/RECORD
